{"Name":" Animaniacs - Lights, Camera, Action! (Europe) (En,Fr,De,Es,It) (Rev 1)","Portrait":"https://raw.githubusercontent.com/libretro-thumbnails/Nintendo_-_Nintendo_DS/master/Named_Boxarts/ Animaniacs - Lights, Camera, Action! (Europe) (En,Fr,De,Es,It) (Rev 1).png","Size":"2M","Region":"EU","Console":"Nintendo DS","DownloadLink":"https://the-eye.eu/public/rom/Nintendo%20DS/5481%20-%20Animaniacs%20-%20Lights%2C%20Camera%2C%20Action%21%20%28Europe%29%20%28En%2CFr%2CDe%2CEs%2CIt%29%20%28Rev%201%29.nds.7z"}