{"Name":" LEGO The Lord of the Rings (Europe) (En,Fr,De,Es,It,Nl,Da) (German dubbed)","Portrait":"https://raw.githubusercontent.com/libretro-thumbnails/Nintendo_-_Nintendo_DS/master/Named_Boxarts/ LEGO The Lord of the Rings (Europe) (En,Fr,De,Es,It,Nl,Da) (German dubbed).png","Size":"99M","Region":"EU","Console":"Nintendo DS","DownloadLink":"https://the-eye.eu/public/rom/Nintendo%20DS/6142%20-%20LEGO%20The%20Lord%20of%20the%20Rings%20%28Europe%29%20%28En%2CFr%2CDe%2CEs%2CIt%2CNl%2CDa%29%20%28German%20dubbed%29.nds.7z"}