{"Name":" Lord of the Rings, The - Aragorn's Quest (Europe) (En,Fr,De,Es,It,Nl) [b]","Portrait":"https://raw.githubusercontent.com/libretro-thumbnails/Nintendo_-_Nintendo_DS/master/Named_Boxarts/ Lord of the Rings, The - Aragorn's Quest (Europe) (En,Fr,De,Es,It,Nl) [b].png","Size":"46M","Region":"EU","Console":"Nintendo DS","DownloadLink":"https://the-eye.eu/public/rom/Nintendo%20DS/5282%20-%20Lord%20of%20the%20Rings%2C%20The%20-%20Aragorn%27s%20Quest%20%28Europe%29%20%28En%2CFr%2CDe%2CEs%2CIt%2CNl%29%20%5Bb%5D.nds.7z"}