{"Name":" Majin Tantei Nougami Neuro - Neuro to Yako no Bishoku Zanmai - Suiri Tsuki - Gourmet & Mystery (Japan)","Portrait":"https://raw.githubusercontent.com/libretro-thumbnails/Nintendo_-_Nintendo_DS/master/Named_Boxarts/Majin Tantei Nougami Neuro - Neuro to Yako no Bishoku Zanmai - Suiri         Tsuki - Gourmet _ Mystery (Japan).png","Size":"34M","Region":"JAP","Console":"Nintendo DS","DownloadLink":"https://the-eye.eu/public/rom/Nintendo%20DS/2580%20-%20Majin%20Tantei%20Nougami%20Neuro%20-%20Neuro%20to%20Yako%20no%20Bishoku%20Zanmai%20-%20Suiri%20Tsuki%20-%20Gourmet%20%26%20Mystery%20%28Japan%29.nds.7z"}