{"Name":" Meine Tierarztpraxis - SOS am Ozean (Europe) (En,De) (NDSi Enhanced) [b]","Portrait":"https://raw.githubusercontent.com/libretro-thumbnails/Nintendo_-_Nintendo_DS/master/Named_Boxarts/Meine Tierarztpraxis - SOS am Ozean (Europe) (En,De) (NDSi         Enhanced).png","Size":"20M","Region":"EU","Console":"Nintendo DS","DownloadLink":"https://the-eye.eu/public/rom/Nintendo%20DS/5249%20-%20Meine%20Tierarztpraxis%20-%20SOS%20am%20Ozean%20%28Europe%29%20%28En%2CDe%29%20%28NDSi%20Enhanced%29%20%5Bb%5D.nds.7z"}