{"Name":" Pferd & Pony - Mein Gestuet - Ein Leben fuer die Pferde (Europe) (En,Fr,De,Es,It) [b]","Portrait":"https://raw.githubusercontent.com/libretro-thumbnails/Nintendo_-_Nintendo_DS/master/Named_Boxarts/ Pferd & Pony - Mein Gestuet - Ein Leben fuer die Pferde (Europe) (En,Fr,De,Es,It) [b].png","Size":"19M","Region":"EU","Console":"Nintendo DS","DownloadLink":"https://the-eye.eu/public/rom/Nintendo%20DS/3677%20-%20Pferd%20%26%20Pony%20-%20Mein%20Gestuet%20-%20Ein%20Leben%20fuer%20die%20Pferde%20%28Europe%29%20%28En%2CFr%2CDe%2CEs%2CIt%29%20%5Bb%5D.nds.7z"}