{"Name":" Simple DS Series Vol. 23 - The Puzzle Quest - Agaria no Kishi (Japan) (Rev 1)","Portrait":"https://raw.githubusercontent.com/libretro-thumbnails/Nintendo_-_Nintendo_DS/master/Named_Boxarts/ Simple DS Series Vol. 23 - The Puzzle Quest - Agaria no Kishi (Japan) (Rev 1).png","Size":"5M","Region":"JAP","Console":"Nintendo DS","DownloadLink":"https://the-eye.eu/public/rom/Nintendo%20DS/4110%20-%20Simple%20DS%20Series%20Vol.%2023%20-%20The%20Puzzle%20Quest%20-%20Agaria%20no%20Kishi%20%28Japan%29%20%28Rev%201%29.nds.7z"}