{"Name":" Snoopy no Aiken DS - Shitte Okitai Inu no Koto, Inu no Nouryoku, Anata no Shitsuke (Japan) [b]","Portrait":"https://raw.githubusercontent.com/libretro-thumbnails/Nintendo_-_Nintendo_DS/master/Named_Boxarts/ Snoopy no Aiken DS - Shitte Okitai Inu no Koto, Inu no Nouryoku, Anata no Shitsuke (Japan) [b].png","Size":"6M","Region":"JAP","Console":"Nintendo DS","DownloadLink":"https://the-eye.eu/public/rom/Nintendo%20DS/4319%20-%20Snoopy%20no%20Aiken%20DS%20-%20Shitte%20Okitai%20Inu%20no%20Koto%2C%20Inu%20no%20Nouryoku%2C%20Anata%20no%20Shitsuke%20%28Japan%29%20%5Bb%5D.nds.7z"}