{"Name":" Zennou Series Vol. 01 - Akiyama Jin Kyouju Kanshuu - Zennou JinJin (Japan)","Portrait":"https://raw.githubusercontent.com/libretro-thumbnails/Nintendo_-_Nintendo_DS/master/Named_Boxarts/ Zennou Series Vol. 01 - Akiyama Jin Kyouju Kanshuu - Zennou JinJin (Japan).png","Size":"1M","Region":"JAP","Console":"Nintendo DS","DownloadLink":"https://the-eye.eu/public/rom/Nintendo%20DS/0543%20-%20Zennou%20Series%20Vol.%2001%20-%20Akiyama%20Jin%20Kyouju%20Kanshuu%20-%20Zennou%20JinJin%20%28Japan%29.nds.7z"}