{"Name":" Ueki no Housoku Shinki Sakuretsu! Nouryokumono Battle (J)(Caravan)","Portrait":"https://raw.githubusercontent.com/libretro-thumbnails/Nintendo_-_Game_Boy_Advance/master/Named_Boxarts/ Ueki no Housoku Shinki Sakuretsu! Nouryokumono Battle (J)(Caravan).png","Size":"3M","Region":"JAP","Console":"GameBoyAdvance","DownloadLink":"https://the-eye.eu/public/rom/Nintendo%20Gameboy%20Advance/2337%20-%20Ueki%20no%20Housoku%20Shinki%20Sakuretsu%21%20Nouryokumono%20Battle%20%28J%29%28Caravan%29.zip"}